PyQt5ElaWidgetTools/ElaWidgetTools.pyd
PyQt5ElaWidgetTools/ElaWidgetTools.pyi
PyQt5ElaWidgetTools/__init__.py
pyqt5_elawidgettools-0.7.4.dist-info/METADATA
pyqt5_elawidgettools-0.7.4.dist-info/WHEEL
pyqt5_elawidgettools-0.7.4.dist-info/top_level.txt
pyqt5_elawidgettools-0.7.4.dist-info/RECORD
