Metadata-Version: 2.4
Name: PyQt5-ElaWidgetTools
Version: 0.7.4
Author: HIllya51
License: MIT
Project-URL: Homepage, https://github.com/HIllya51/PyElaWidgetTools
Project-URL: Repository, https://github.com/HIllya51/PyElaWidgetTools
Requires-Dist: PyQt5
Dynamic: author
Dynamic: license
Dynamic: project-url
Dynamic: requires-dist
